pypage.py
pypage-2.2.1.dist-info/licenses/LICENSE.txt
pypage-2.2.1.dist-info/METADATA
pypage-2.2.1.dist-info/WHEEL
pypage-2.2.1.dist-info/entry_points.txt
pypage-2.2.1.dist-info/top_level.txt
pypage-2.2.1.dist-info/RECORD
