Metadata-Version: 2.4
Name: pypage
Version: 2.2.1
Summary:  Light-weight Python Templating Engine
Home-page: https://github.com/arjun-menon/pypage
Download-URL: https://github.com/arjun-menon/pypage/archive/v2.2.1.tar.gz
Author: Arjun G. Menon
Author-email: contact@arjungmenon.com
License: Apache-2.0
Keywords: templating engine text processing static generator,templating engine,text processing,template,templates
Classifier: Topic :: Text Processing
Classifier: Intended Audience :: Developers
Classifier: Topic :: Internet :: WWW/HTTP
Classifier: Topic :: Internet :: WWW/HTTP :: Dynamic Content
Classifier: Topic :: Text Processing :: Markup :: HTML
Classifier: License :: OSI Approved :: Apache Software License
Classifier: Topic :: Software Development :: Libraries :: Python Modules
Classifier: Intended Audience :: Developers
Classifier: Environment :: Console
Classifier: Environment :: Web Environment
Classifier: Operating System :: OS Independent
Classifier: Programming Language :: Python :: Implementation :: CPython
Classifier: Programming Language :: Python :: Implementation :: PyPy
Classifier: Programming Language :: Python :: 2
Classifier: Programming Language :: Python :: 3
License-File: LICENSE.txt
Dynamic: author
Dynamic: author-email
Dynamic: classifier
Dynamic: description
Dynamic: download-url
Dynamic: home-page
Dynamic: keywords
Dynamic: license
Dynamic: license-file
Dynamic: summary
